{"version":1,"resource":"file:///home/p4imon/Documents/INT/searchfor%20copy.sh","entries":[{"id":"P8vm.sh","timestamp":1665078884910},{"id":"uuZc.sh","timestamp":1665078986897},{"id":"Tosn.sh","timestamp":1665079064290},{"id":"PGl6.sh","timestamp":1665079401580},{"id":"M1i3.sh","timestamp":1665129109287},{"id":"gDoS.sh","timestamp":1665129121160},{"id":"Ms7T.sh","timestamp":1665129139530},{"id":"s521.sh","timestamp":1665129158440},{"id":"zuYB.sh","timestamp":1665129222290},{"id":"HbAv.sh","timestamp":1665129232997},{"id":"zNvw.sh","source":"undoRedo.source","timestamp":1665131756353}]}